tubebank.py
tubebank-1.0.dist-info/LICENSE
tubebank-1.0.dist-info/METADATA
tubebank-1.0.dist-info/WHEEL
tubebank-1.0.dist-info/top_level.txt
tubebank-1.0.dist-info/RECORD
