Metadata-Version: 2.1
Name: tubebank
Version: 1.0
Summary: Implementation of the Zukauskas correlations for crossflow over banks of tubes.
Author: Ellie Litwack
License: UNKNOWN
Platform: UNKNOWN
Classifier: Programming Language :: Python :: 3
Classifier: License :: OSI Approved :: MIT License
Classifier: Operating System :: OS Independent
Requires-Python: >=3.8, <3.11
License-File: LICENSE
Requires-Dist: scipy (>=0.10)
Requires-Dist: numpy
